pvmlib/__init__.py
pvmlib/info_lib.py
pvmlib/context/__init__.py
pvmlib/context/request_context.py
pvmlib/database/__init__.py
pvmlib/database/database.py
pvmlib/database/lifespan.py
pvmlib/exceptions/__init__.py
pvmlib/exceptions/error_response.py
pvmlib/fork/__init__.py
pvmlib/fork/actions.py
pvmlib/fork/fork.py
pvmlib/healthchecks/__init__.py
pvmlib/healthchecks/liveness.py
pvmlib/healthchecks/readiness.py
pvmlib/logs/__init__.py
pvmlib/logs/logger.py
pvmlib/logs/models/__init__.py
pvmlib/logs/models/logs_model.py
pvmlib/logs/utils/__init__.py
pvmlib/logs/utils/dicctionary_types.py
pvmlib/middlewares/__init__.py
pvmlib/middlewares/request_middleware.py
pvmlib/patterns/__init__.py
pvmlib/patterns/circuit_breaker.py
pvmlib/patterns/decorator.py
pvmlib/responses/__init__.py
pvmlib/responses/error_response.py
pvmlib/responses/success_response.py
pvmlib/schemas/__init__.py
pvmlib/schemas/errors_schema.py
pvmlib/schemas/healthcheck_reponse_schema.py
pvmlib/schemas/response_meta_schema.py
pvmlib/schemas/success_schema.py
pvmlib/utils/__init__.py
pvmlib/utils/dependecy_check.py
pvmlib/utils/error_message_default.py
pvmlib/utils/request_helper_util.py
pvmlib/utils/utils.py
pvmlib-1.9.11.dist-info/licenses/LICENSE
pvmlib-1.9.11.dist-info/METADATA
pvmlib-1.9.11.dist-info/WHEEL
pvmlib-1.9.11.dist-info/top_level.txt
pvmlib-1.9.11.dist-info/RECORD
