Metadata-Version: 2.4
Name: pvmlib
Version: 1.9.11
Summary: Python library for PVM
Home-page: 
Author: Henrry Cañedo
Author-email: henrry.canedo@coppel.com
License: MIT
Classifier: Programming Language :: Python :: 3
Classifier: License :: OSI Approved :: MIT License
Classifier: Operating System :: OS Independent
Requires-Python: >=3.12
License-File: LICENSE
Requires-Dist: google-cloud-logging>=3.12.1
Requires-Dist: pydantic-settings>=2.9.1
Requires-Dist: pydantic>=2.11.4
Requires-Dist: pytz>=2025.2
Requires-Dist: circuitbreaker>=2.1.3
Requires-Dist: tenacity>=9.1.2
Requires-Dist: pybreaker>=1.3.0
Requires-Dist: aiohttp>=3.11.18
Requires-Dist: starlette>=0.49.1
Requires-Dist: urllib3>=2.6.2
Requires-Dist: charset_normalizer<3.0.0,>=2.0.0
Requires-Dist: motor>=3.7.0
Requires-Dist: colorama>=0.4.6
Dynamic: author
Dynamic: author-email
Dynamic: classifier
Dynamic: description
Dynamic: description-content-type
Dynamic: license
Dynamic: license-file
Dynamic: requires-dist
Dynamic: requires-python
Dynamic: summary
